{
    "6129000070": {
        "phone": "+998937897147",
        "username": "....",
        "id": 6129000070
    },
    "7629836653": {
        "phone": "+998933351511",
        "username": "\uf8ff",
        "id": 7629836653
    },
    "880888292": {
        "phone": "+998993656700",
        "username": "Bunyodbek",
        "id": 880888292
    },
    "153987753": {
        "phone": "+998936326700",
        "username": "Sadoqatxon Adhamjonovna",
        "id": 153987753
    },
    "6434670142": {
        "phone": "+998771182244",
        "username": "\ud835\udc13\ud835\udc1e\ud835\udc26\ud835\udc2e\ud835\udc2b\ud835\udc1b\ud835\udc1e\ud835\udc24 \ud835\udc19\ud835\udc22\ud835\udc32\ud835\udc28\ud835\udc1d\ud835\udc2e\ud835\udc25\ud835\udc25\ud835\udc1a\ud835\udc32\ud835\udc1e\ud835\udc2f",
        "id": 6434670142
    }
}